COPYING
MANIFEST.in
README.md
setup.py
mamba/__init__.py
mamba/application_factory.py
mamba/cli.py
mamba/error.py
mamba/example.py
mamba/example_collector.py
mamba/example_group.py
mamba/formatters.py
mamba/loader.py
mamba/nodetransformers.py
mamba/reporter.py
mamba/runnable.py
mamba/runners.py
mamba/settings.py
mamba.egg-info/PKG-INFO
mamba.egg-info/SOURCES.txt
mamba.egg-info/dependency_links.txt
mamba.egg-info/entry_points.txt
mamba.egg-info/not-zip-safe
mamba.egg-info/requires.txt
mamba.egg-info/top_level.txt
mamba/infrastructure/__init__.py
mamba/infrastructure/code_coverage.py